odoo9_addon_account_invoice_search_by_reference-9.0.1.0.0-py2.7-nspkg.pth
odoo9_addon_account_invoice_search_by_reference-9.0.1.0.0.dist-info/DESCRIPTION.rst
odoo9_addon_account_invoice_search_by_reference-9.0.1.0.0.dist-info/METADATA
odoo9_addon_account_invoice_search_by_reference-9.0.1.0.0.dist-info/RECORD
odoo9_addon_account_invoice_search_by_reference-9.0.1.0.0.dist-info/WHEEL
odoo9_addon_account_invoice_search_by_reference-9.0.1.0.0.dist-info/metadata.json
odoo9_addon_account_invoice_search_by_reference-9.0.1.0.0.dist-info/namespace_packages.txt
odoo9_addon_account_invoice_search_by_reference-9.0.1.0.0.dist-info/top_level.txt
odoo_addons/account_invoice_search_by_reference/README.rst
odoo_addons/account_invoice_search_by_reference/__init__.py
odoo_addons/account_invoice_search_by_reference/__openerp__.py
odoo_addons/account_invoice_search_by_reference/model/__init__.py
odoo_addons/account_invoice_search_by_reference/model/account_invoice.py
